python_semantic_release-10.5.2.dist-info/licenses/LICENSE
semantic_release/__init__.py
semantic_release/__main__.py
semantic_release/const.py
semantic_release/enums.py
semantic_release/errors.py
semantic_release/gitproject.py
semantic_release/globals.py
semantic_release/helpers.py
semantic_release/py.typed
semantic_release/changelog/__init__.py
semantic_release/changelog/context.py
semantic_release/changelog/release_history.py
semantic_release/changelog/template.py
semantic_release/cli/__init__.py
semantic_release/cli/changelog_writer.py
semantic_release/cli/cli_context.py
semantic_release/cli/config.py
semantic_release/cli/const.py
semantic_release/cli/github_actions_output.py
semantic_release/cli/masking_filter.py
semantic_release/cli/util.py
semantic_release/cli/commands/__init__.py
semantic_release/cli/commands/changelog.py
semantic_release/cli/commands/generate_config.py
semantic_release/cli/commands/main.py
semantic_release/cli/commands/publish.py
semantic_release/cli/commands/version.py
semantic_release/commit_parser/__init__.py
semantic_release/commit_parser/_base.py
semantic_release/commit_parser/angular.py
semantic_release/commit_parser/emoji.py
semantic_release/commit_parser/scipy.py
semantic_release/commit_parser/tag.py
semantic_release/commit_parser/token.py
semantic_release/commit_parser/util.py
semantic_release/commit_parser/conventional/__init__.py
semantic_release/commit_parser/conventional/options.py
semantic_release/commit_parser/conventional/options_monorepo.py
semantic_release/commit_parser/conventional/parser.py
semantic_release/commit_parser/conventional/parser_monorepo.py
semantic_release/data/templates/conventional/md/.release_notes.md.j2
semantic_release/data/templates/conventional/md/CHANGELOG.md.j2
semantic_release/data/templates/conventional/md/.components/changelog_header.md.j2
semantic_release/data/templates/conventional/md/.components/changelog_init.md.j2
semantic_release/data/templates/conventional/md/.components/changelog_update.md.j2
python_semantic_release-10.5.2.dist-info/METADATA
python_semantic_release-10.5.2.dist-info/WHEEL
python_semantic_release-10.5.2.dist-info/entry_points.txt
python_semantic_release-10.5.2.dist-info/top_level.txt
python_semantic_release-10.5.2.dist-info/RECORD
